{"cameraMode":{"drawMode":0,"name":"Shaded","section":"Shading Mode"},"sceneLighting":true,"audioPlay":false,"sceneViewState":{"m_AlwaysRefresh":false,"showFog":true,"showSkybox":true,"showFlares":true,"showImageEffects":true,"showParticleSystems":true,"showVisualEffectGraphs":true,"m_FxEnabled":true},"in2DMode":false,"pivot":{"x":847.0,"y":1325.0,"z":0.0},"rotation":{"x":0.12455978244543076,"y":-0.076273113489151,"z":0.010422376915812493,"w":0.98930823802948},"size":464.71759033203127,"orthographic":true}